{
    "relays": {
        "1": {
            "id": "relay1",
            "pin": 22,
            "address": "0x46",
            "on": "LOW",
            "off": "HIGH"
        },
        "2": {
            "id": "relay2",
            "pin": 27,
            "address": "0x47",
            "on": "LOW",
            "off": "HIGH"
        },
        "3": {
            "id": "relay3",
            "pin": 17,
            "address": "0x48",
            "on": "HIGH",
            "off": "LOW"
        },
        "4": {
            "id": "relay4",
            "pin": 4,
            "address": "0x49",
            "on": "HIGH",
            "off": "LOW"
        },
        "5": {
            "id": "relay5",
            "pin": 24,
            "address": "0x4A",
            "on": "HIGH",
            "off": "LOW"
        },
        "6": {
            "id": "relay6",
            "pin": 23,
            "address": "0x4B",
            "on": "HIGH",
            "off": "LOW"
        },
        "7": {
            "id": "main",
            "pin": 12,
            "address": "0x4C",
            "on": "HIGH",
            "off": "LOW"
        }
    }
}